py_sdk/__init__.py
py_sdk/betanet.py
py_sdk/mainnet.py
py_sdk/testnet.py
py_algorand_nft_sdk-0.0.2.dist-info/LICENSE
py_algorand_nft_sdk-0.0.2.dist-info/METADATA
py_algorand_nft_sdk-0.0.2.dist-info/WHEEL
py_algorand_nft_sdk-0.0.2.dist-info/top_level.txt
py_algorand_nft_sdk-0.0.2.dist-info/RECORD
