Metadata-Version: 2.1
Name: py-algorand-nft-sdk
Version: 0.0.2
Summary: For creating and updating NFTs on the algorand testnet, devnet, betanet and mainet networks. Can also be used to generate accounts on the afore mentioned networks
Home-page: https://github.com/Apostrophe-Corp/0xAuction/blob/beta/Algorand-NFT-SDK/python-algorand-sdk/README.md
Author: Apostrophe Corp
Author-email: goonerlabs@gmail.com
Classifier: Programming Language :: Python :: 3
Classifier: License :: OSI Approved :: MIT License
Classifier: Operating System :: OS Independent
Requires-Python: >=3.10
License-File: LICENSE
